AUTHORS.rst
CONTRIBUTING.rst
HISTORY.rst
LICENSE
MANIFEST.in
README.rst
blowfish.c
setup.cfg
setup.py
ectoken/__init__.py
ectoken/ectoken.py
ectoken.egg-info/PKG-INFO
ectoken.egg-info/SOURCES.txt
ectoken.egg-info/dependency_links.txt
ectoken.egg-info/not-zip-safe
ectoken.egg-info/top_level.txt