Metadata-Version: 1.1
Name: ectoken
Version: 0.4
Summary: Python implementation of EdgeCast Token (ectoken_generate).
Home-page: https://github.com/sebest/ectoken-py
Author: Sébastien Estienne
Author-email: sebastien.estienne@gmail.com
License: BSD
Keywords: ectoken
Platform: UNKNOWN
Classifier: Development Status :: 5 - Production/Stable
Classifier: Intended Audience :: Developers
Classifier: License :: OSI Approved :: BSD License
Classifier: Natural Language :: English
Classifier: Programming Language :: Python :: 2
Classifier: Programming Language :: Python :: 2.6
Classifier: Programming Language :: Python :: 2.7
Classifier: Programming Language :: Python :: 3
Classifier: Programming Language :: Python :: 3.3
